{
  "kind": "collectionType",
  "collectionName": "products",
  "info": {
    "singularName": "product",
    "pluralName": "products",
    "displayName": "Product",
    "description": ""
  },
  "options": {
    "draftAndPublish": true
  },
  "pluginOptions": {},
  "attributes": {
    "name": {
      "type": "string"
    },
    "description": {
      "type": "text"
    },
    "images": {
      "type": "media",
      "multiple": true,
      "required": false,
      "allowedTypes": [
        "images",
        "files",
        "videos",
        "audios"
      ]
    },
    "smallSize_inStock": {
      "type": "integer"
    },
    "mediumSize_inStock": {
      "type": "integer"
    },
    "largeSize_inStock": {
      "type": "integer"
    },
    "extraLargeSize_inStock": {
      "type": "integer"
    },
    "price": {
      "type": "decimal"
    },
    "UUID": {
      "type": "uid"
    }
  }
}
